thirdweb/.DS_Store
thirdweb/__init__.py
thirdweb/abi/__init__.py
thirdweb/abi/airdrop_erc1155.py
thirdweb/abi/airdrop_erc1155_claimable.py
thirdweb/abi/airdrop_erc20.py
thirdweb/abi/airdrop_erc20_claimable.py
thirdweb/abi/airdrop_erc721.py
thirdweb/abi/airdrop_erc721_claimable.py
thirdweb/abi/app_u_r_i.py
thirdweb/abi/batch_mint_metadata.py
thirdweb/abi/context.py
thirdweb/abi/contract_metadata.py
thirdweb/abi/contract_metadata_logic.py
thirdweb/abi/contract_metadata_storage.py
thirdweb/abi/contract_publisher.py
thirdweb/abi/counters.py
thirdweb/abi/currency_transfer_lib.py
thirdweb/abi/default_operator_filterer.py
thirdweb/abi/default_operator_filterer_upgradeable.py
thirdweb/abi/delayed_reveal.py
thirdweb/abi/direct_listings_logic.py
thirdweb/abi/direct_listings_storage.py
thirdweb/abi/drop.py
thirdweb/abi/drop1155.py
thirdweb/abi/drop_erc1155.py
thirdweb/abi/drop_erc20.py
thirdweb/abi/drop_erc721.py
thirdweb/abi/drop_single_phase.py
thirdweb/abi/drop_single_phase1155.py
thirdweb/abi/droperc1155_v2.py
thirdweb/abi/droperc20_v2.py
thirdweb/abi/droperc721_v3.py
thirdweb/abi/dropsinglephase1155_v1.py
thirdweb/abi/dropsinglephase_v1.py
thirdweb/abi/e_i_p712_chainless_domain.py
thirdweb/abi/ecdsa.py
thirdweb/abi/edition_stake.py
thirdweb/abi/eip712.py
thirdweb/abi/english_auctions_logic.py
thirdweb/abi/english_auctions_storage.py
thirdweb/abi/enumerable_set.py
thirdweb/abi/erc1155.py
thirdweb/abi/erc1155_base.py
thirdweb/abi/erc1155_delayed_reveal.py
thirdweb/abi/erc1155_drop.py
thirdweb/abi/erc1155_holder.py
thirdweb/abi/erc1155_lazy_mint.py
thirdweb/abi/erc1155_preset_upgradeable.py
thirdweb/abi/erc1155_receiver.py
thirdweb/abi/erc1155_signature_mint.py
thirdweb/abi/erc165.py
thirdweb/abi/erc1967_proxy.py
thirdweb/abi/erc1967_upgrade.py
thirdweb/abi/erc20.py
thirdweb/abi/erc20_base.py
thirdweb/abi/erc20_drop.py
thirdweb/abi/erc20_drop_vote.py
thirdweb/abi/erc20_permit.py
thirdweb/abi/erc20_signature_mint.py
thirdweb/abi/erc20_signature_mint_vote.py
thirdweb_sdk-3.1.0.dist-info/LICENSE
thirdweb_sdk-3.1.0.dist-info/METADATA
thirdweb_sdk-3.1.0.dist-info/WHEEL
thirdweb_sdk-3.1.0.dist-info/entry_points.txt
thirdweb_sdk-3.1.0.dist-info/RECORD
