Metadata-Version: 2.1
Name: thirdweb-sdk
Version: 3.1.0
Summary: 
Author: thirdweb
Author-email: sdk@thirdweb.com
Requires-Python: >=3.7.1
Classifier: Programming Language :: Python :: 3
Classifier: Programming Language :: Python :: 3.8
Classifier: Programming Language :: Python :: 3.9
Classifier: Programming Language :: Python :: 3.10
Classifier: Programming Language :: Python :: 3.11
Requires-Dist: cbor2 (>=5.4.3,<6.0.0)
Requires-Dist: dacite (>=1.6.0,<2.0.0)
Requires-Dist: mypy-extensions (>=0.4.3,<0.5.0)
Requires-Dist: pyee (>=9.0.4,<10.0.0)
Requires-Dist: pymerkle (>=2.0.2,<3.0.0)
Requires-Dist: pytz (>=2022.1,<2023.0)
Requires-Dist: thirdweb-contract-wrappers (>=2.0.4,<3.0.0)
Requires-Dist: thirdweb-eth-account (>=0.6.6,<0.7.0)
Requires-Dist: web3 (==5.27.0)
